README.txt
setup.cfg
setup.py
collective/__init__.py
collective.croppingimagefield.egg-info/PKG-INFO
collective.croppingimagefield.egg-info/SOURCES.txt
collective.croppingimagefield.egg-info/dependency_links.txt
collective.croppingimagefield.egg-info/entry_points.txt
collective.croppingimagefield.egg-info/namespace_packages.txt
collective.croppingimagefield.egg-info/not-zip-safe
collective.croppingimagefield.egg-info/paster_plugins.txt
collective.croppingimagefield.egg-info/requires.txt
collective.croppingimagefield.egg-info/top_level.txt
collective/croppingimagefield/__init__.py
collective/croppingimagefield/fields.py
collective/croppingimagefield/tests.py