Metadata-Version: 1.0
Name: collective.croppingimagefield
Version: 0.1beta
Summary: Provides an image field that can crop, zoom or scale an image instead of just scaling it
Home-page: http://svn.plone.org/svn/collective/collective.croppingimagefield
Author: Jonathan Riboux
Author-email: jonathan.riboux@gmail.com
License: GPL
Platform: UNKNOWN
Classifier: Framework :: Plone
Classifier: Programming Language :: Python
Classifier: Topic :: Software Development :: Libraries :: Python Modules
Classifier: Development Status :: 4 - Beta
Classifier: Intended Audience :: Developers
Classifier: License :: OSI Approved :: GNU General Public License (GPL)
Classifier: Operating System :: OS Independent
Classifier: Programming Language :: Python :: 2.4
Classifier: Topic :: Multimedia :: Graphics :: Graphics Conversion
Classifier: Topic :: Software Development
